tpds_extension/demo_keystream_fota/extension.yaml
tpds_extension/demo_keystream_fota/setup.py
tpds_extension/demo_keystream_fota/version.py
tpds_extension/demo_keystream_fota/backend/__init__.py
tpds_extension/demo_keystream_fota/backend/FOTA/FOTA.py
tpds_extension/demo_keystream_fota/backend/FOTA/__init__.py
tpds_extension/demo_keystream_fota/backend/FOTA/api.py
tpds_extension/demo_keystream_fota/backend/FOTA/helper.py
tpds_extension/demo_keystream_fota/backend/Images/FOTA-Trust-Manager.jpg
tpds_extension/demo_keystream_fota/backend/api/__init__.py
tpds_extension/demo_keystream_fota/backend/api/apis.py
tpds_extension/demo_keystream_fota/backend/resources/reset.txt
tpds_extension/demo_keystream_fota/frontend/Fota.jpg
tpds_extension/demo_keystream_fota/frontend/InterVariable-CWi-zmRD.woff2
tpds_extension/demo_keystream_fota/frontend/InterVariable-Italic-d6KXgdvN.woff2
tpds_extension/demo_keystream_fota/frontend/index-BBKbfZ_X.css
tpds_extension/demo_keystream_fota/frontend/index-CJVXS62M.js
tpds_extension/demo_keystream_fota/frontend/index.html
tpds_extension/demo_keystream_fota/frontend/primeicons-C6QP2o4f.woff2
tpds_extension/demo_keystream_fota/frontend/primeicons-DMOk5skT.eot
tpds_extension/demo_keystream_fota/frontend/primeicons-Dr5RGzOO.svg
tpds_extension/demo_keystream_fota/frontend/primeicons-MpK4pl85.ttf
tpds_extension/demo_keystream_fota/frontend/primeicons-WjwUDZjB.woff
tpds_extension_demo_keystream_fota-1.0.0.dist-info/licenses/LICENSE
tpds_extension_demo_keystream_fota-1.0.0.dist-info/METADATA
tpds_extension_demo_keystream_fota-1.0.0.dist-info/WHEEL
tpds_extension_demo_keystream_fota-1.0.0.dist-info/top_level.txt
tpds_extension_demo_keystream_fota-1.0.0.dist-info/RECORD
