Metadata-Version: 2.4
Name: tpds-extension-demo-keystream-fota
Version: 1.0.0
Summary: Microchip(SPG) Trust Platform - Keystream FOTA Demo
Maintainer-email: Microchip Technology <SPG.Tools@microchip.com>
License: (c) 2025 to present - Copyright Microchip Technology Inc. and its subsidiaries.
Classifier: License :: Other/Proprietary License
Classifier: Development Status :: 4 - Beta
Classifier: Programming Language :: Python :: 3
Classifier: Operating System :: OS Independent
Requires-Python: >=3.10
License-File: LICENSE
Requires-Dist: pyserial
Requires-Dist: pykitinfo
Requires-Dist: tpds-extension-keystream-connect
Provides-Extra: dev
Requires-Dist: flake8; extra == "dev"
Requires-Dist: black; extra == "dev"
Requires-Dist: isort; extra == "dev"
Requires-Dist: mypy; extra == "dev"
Provides-Extra: test
Requires-Dist: pytest-cov; extra == "test"
Requires-Dist: pytest-mock; extra == "test"
Requires-Dist: pytest-integration; extra == "test"
Dynamic: license-file
